whatsapp_mcp/__init__.py
whatsapp_mcp/server.py
whatsapp_mcp-0.1.0.dist-info/LICENSE
whatsapp_mcp-0.1.0.dist-info/METADATA
whatsapp_mcp-0.1.0.dist-info/WHEEL
whatsapp_mcp-0.1.0.dist-info/entry_points.txt
whatsapp_mcp-0.1.0.dist-info/RECORD
